pyCARM/__init__.py
pyCARM/basic.py
pyCARM/fixed_route.py
pyCARM/flexible_route.py
pycarm-1.0.3.dist-info/licenses/LICENSE
pycarm-1.0.3.dist-info/METADATA
pycarm-1.0.3.dist-info/WHEEL
pycarm-1.0.3.dist-info/top_level.txt
pycarm-1.0.3.dist-info/RECORD
