Metadata-Version: 2.4
Name: pyCARM
Version: 1.0.3
Summary: pyCARM: Cellular Automata for Aircraft Arrival Modelling
Home-page: https://github.com/IkeoluwaSta/pyCARM
Author: The Hong Kong University of Science
Author-email: iiogedengbe@connect.ust.hk
Project-URL: Source Code, https://github.com/IkeoluwaSta/pyCARM
Project-URL: Bug Tracker, https://github.com/IkeoluwaSta/pyCARM/issues
Classifier: Programming Language :: Python :: 3
Classifier: Programming Language :: Python :: 3.4
Classifier: Programming Language :: Python :: 3.5
Classifier: Programming Language :: Python :: 3.6
Classifier: Programming Language :: Python :: 3.7
Classifier: Programming Language :: Python :: 3.8
Classifier: License :: OSI Approved :: MIT License
Classifier: Operating System :: OS Independent
Requires-Python: >=3
License-File: LICENSE
Requires-Dist: numpy
Requires-Dist: matplotlib
Requires-Dist: distinctipy
Dynamic: author
Dynamic: author-email
Dynamic: classifier
Dynamic: description
Dynamic: description-content-type
Dynamic: home-page
Dynamic: license-file
Dynamic: project-url
Dynamic: requires-dist
Dynamic: requires-python
Dynamic: summary
